{"pathArr":[],"metaData":{"title":"운영체제"},"content":"\n> An operating system (OS) is system software that manages computer hardware, software resources, and provides common services for computer programs. 위키피디아.\n\n인프런의 [운영체제 공룡책 강의](https://www.inflearn.com/course/운영체제-공룡책-전공강의/dashboard)로학습을했다. 사진 자료는 Operating System Concepts 10th에서 발췌해왔다.\n\n[Introduction & O/S Structures](introduction)\n\n[Processes](process)\n\n[Thread & Concurrency](thread)\n\n[CPU Scheduling](scheduling)\n\n[Synchronization Tools](sync_tools)\n\n[Synchronization Examples](sync_examples)\n\n[Deadlocks](deadlocks)\n\n[Main Memory](main_memory)\n\n[Virtual Memory](virtual_memory)\n\n[Storage Management](storage)\n\n[Security & Protection](security_and_protection)\n","path":"cs/os/index.md"}